progress_basic/__init__.py
progress_basic/progress_bar.py
progress_basic/progress_basic.py
progress_basic/format/color_text.py
progress_basic-0.5.dist-info/METADATA
progress_basic-0.5.dist-info/WHEEL
progress_basic-0.5.dist-info/top_level.txt
progress_basic-0.5.dist-info/RECORD
