Metadata-Version: 2.1
Name: progress_basic
Version: 0.5
Summary: A Python library for displaying progress indicators and progress bars in the console with customizable messages and colors.
Home-page: https://github.com/leonardogonzalolaura/progress_basic
Author: leonardogonzalolaura
Author-email: glleonardodaniel@gmail.com
Classifier: Programming Language :: Python :: 3
Classifier: License :: OSI Approved :: MIT License
Classifier: Operating System :: OS Independent
Requires-Python: >=3.6
